README.md
setup.py
pyleapcard/CardEvent.py
pyleapcard/CardOverview.py
pyleapcard/PyLeapCard.py
pyleapcard/__init__.py
pyleapcard.egg-info/PKG-INFO
pyleapcard.egg-info/SOURCES.txt
pyleapcard.egg-info/dependency_links.txt
pyleapcard.egg-info/requires.txt
pyleapcard.egg-info/top_level.txt