Metadata-Version: 2.1
Name: pyleapcard
Version: 0.1.9
Summary: Python Leap Card API (Unofficial). Access your card balance and journey history for Ireland's public transport smart card.
Home-page: https://github.com/skhg/pyleapcard
Author: Jack Higgins
Author-email: pypi@jackhiggins.ie
License: MIT
Keywords: leap card public transport smart card api travel ireland
Platform: UNKNOWN
Classifier: Development Status :: 4 - Beta
Classifier: License :: OSI Approved :: MIT License
Classifier: Programming Language :: Python :: 2.7
Classifier: Programming Language :: Python :: 3.6
